lpu/VERSION
lpu/__init__.py
lpu/backends/__init__.py
lpu/backends/safe_cython.cpython-36m-i386-linux-gnu.so
lpu/backends/safe_cython.py
lpu/backends/safe_logging.cpython-36m-i386-linux-gnu.so
lpu/backends/safe_logging.py
lpu/commands/__init__.py
lpu/commands/abspath.cpython-36m-i386-linux-gnu.so
lpu/commands/abspath.py
lpu/commands/clean_parallel.cpython-36m-i386-linux-gnu.so
lpu/commands/clean_parallel.py
lpu/commands/dialog.cpython-36m-i386-linux-gnu.so
lpu/commands/dialog.py
lpu/commands/exec_parallel.cpython-36m-i386-linux-gnu.so
lpu/commands/exec_parallel.py
lpu/commands/guess_langcode.cpython-36m-i386-linux-gnu.so
lpu/commands/guess_langcode.py
lpu/commands/progress.cpython-36m-i386-linux-gnu.so
lpu/commands/progress.py
lpu/commands/random_split.cpython-36m-i386-linux-gnu.so
lpu/commands/random_split.py
lpu/commands/wait_files.cpython-36m-i386-linux-gnu.so
lpu/commands/wait_files.py
lpu/common/__init__.py
lpu/common/colors.cpython-36m-i386-linux-gnu.so
lpu/common/colors.pxd
lpu/common/colors.py
lpu/common/compat.cpython-36m-i386-linux-gnu.so
lpu/common/compat.pxd
lpu/common/compat.py
lpu/common/config.cpython-36m-i386-linux-gnu.so
lpu/common/config.pxd
lpu/common/config.py
lpu/common/dialog.cpython-36m-i386-linux-gnu.so
lpu/common/dialog.py
lpu/common/environ.cpython-36m-i386-linux-gnu.so
lpu/common/environ.pxd
lpu/common/environ.py
lpu/common/files.cpython-36m-i386-linux-gnu.so
lpu/common/files.py
lpu/common/logging.cpython-36m-i386-linux-gnu.so
lpu/common/logging.pxd
lpu/common/logging.py
lpu/common/numbers.cpython-36m-i386-linux-gnu.so
lpu/common/numbers.pxd
lpu/common/numbers.py
lpu/common/progress.cpython-36m-i386-linux-gnu.so
lpu/common/progress.pxd
lpu/common/progress.py
lpu/common/validation.cpython-36m-i386-linux-gnu.so
lpu/common/validation.py
lpu/common/vocab.cpython-36m-i386-linux-gnu.so
lpu/common/vocab.pxd
lpu/common/vocab.py
lpu/data_structs/__init__.py
lpu-0.2.10.dist-info/METADATA
lpu-0.2.10.dist-info/RECORD
lpu-0.2.10.dist-info/WHEEL
lpu-0.2.10.dist-info/entry_points.txt
lpu-0.2.10.dist-info/top_level.txt
