Metadata-Version: 2.1
Name: lpu
Version: 0.2.10
Summary: A Language Processing Utility
Home-page: https://github.com/akivajp/lpu
Author: Akiva Miura
Author-email: akiva.miura@gmail.com
License: MIT
Keywords: CL,NLP,computational linguistics,natural language processing
Platform: UNKNOWN
Classifier: Programming Language :: Python
Classifier: Programming Language :: Python :: 3.5
Classifier: Programming Language :: Python :: 3.6
Classifier: Programming Language :: Python :: 3.7
Classifier: Topic :: Utilities
